bst/__init__.py
bst/lib.py
ran_bst-2.1.0.dist-info/LICENSE
ran_bst-2.1.0.dist-info/METADATA
ran_bst-2.1.0.dist-info/WHEEL
ran_bst-2.1.0.dist-info/top_level.txt
ran_bst-2.1.0.dist-info/RECORD
