Metadata-Version: 2.1
Name: ran-bst
Version: 2.1.0
Summary: A class for binary search trees.
Home-page: https://github.com/01-ERFA/binary-search-tree-package
Author: Ran
Author-email: star01-fym@gmail.com
License: MIT
Classifier: Programming Language :: Python :: 3
Classifier: License :: OSI Approved :: MIT License
Classifier: Operating System :: OS Independent
License-File: LICENSE
